AUTHORS
COPYING
INSTALL
MANIFEST.in
NEWS
README.md
ez_setup.py
setup.cfg
setup.py
SL_RBTools.egg-info/PKG-INFO
SL_RBTools.egg-info/SOURCES.txt
SL_RBTools.egg-info/dependency_links.txt
SL_RBTools.egg-info/entry_points.txt
SL_RBTools.egg-info/pbr.json
SL_RBTools.egg-info/requires.txt
SL_RBTools.egg-info/top_level.txt
contrib/P4Tool.txt
contrib/README.P4Tool
contrib/installers/windows/scripts/get-version.py
contrib/internal/release.py
rbtools/__init__.py
rbtools/tests.py
rbtools/api/__init__.py
rbtools/api/cache.py
rbtools/api/capabilities.py
rbtools/api/client.py
rbtools/api/decode.py
rbtools/api/decorators.py
rbtools/api/errors.py
rbtools/api/factory.py
rbtools/api/request.py
rbtools/api/resource.py
rbtools/api/tests.py
rbtools/api/utils.py
rbtools/api/transport/__init__.py
rbtools/api/transport/sync.py
rbtools/clients/__init__.py
rbtools/clients/bazaar.py
rbtools/clients/clearcase.py
rbtools/clients/cvs.py
rbtools/clients/errors.py
rbtools/clients/git.py
rbtools/clients/mercurial.py
rbtools/clients/perforce.py
rbtools/clients/plastic.py
rbtools/clients/svn.py
rbtools/clients/tfs.py
rbtools/clients/tests/__init__.py
rbtools/clients/tests/test_bzr.py
rbtools/clients/tests/test_git.py
rbtools/clients/tests/test_mercurial.py
rbtools/clients/tests/test_p4.py
rbtools/clients/tests/test_svn.py
rbtools/commands/__init__.py
rbtools/commands/api_get.py
rbtools/commands/attach.py
rbtools/commands/clearcache.py
rbtools/commands/close.py
rbtools/commands/diff.py
rbtools/commands/install.py
rbtools/commands/land.py
rbtools/commands/list_repo_types.py
rbtools/commands/login.py
rbtools/commands/logout.py
rbtools/commands/main.py
rbtools/commands/patch.py
rbtools/commands/post.py
rbtools/commands/publish.py
rbtools/commands/setup_repo.py
rbtools/commands/stamp.py
rbtools/commands/status.py
rbtools/commands/tests/__init__.py
rbtools/commands/tests/test_post.py
rbtools/helpers/__init__.py
rbtools/helpers/hgext.py
rbtools/hooks/__init__.py
rbtools/hooks/common.py
rbtools/hooks/git.py
rbtools/testing/__init__.py
rbtools/testing/testcase.py
rbtools/utils/__init__.py
rbtools/utils/aliases.py
rbtools/utils/appdirs.py
rbtools/utils/checks.py
rbtools/utils/commands.py
rbtools/utils/console.py
rbtools/utils/diffs.py
