Metadata-Version: 1.2
Name: SL-RBTools
Version: 0.7.12a0.dev0
Summary: Command line tools for use with Review Board
Home-page: http://www.reviewboard.org/
Maintainer: Christian Hammond
Maintainer-email: chipx86@chipx86.com
License: MIT
Download-URL: http://downloads.reviewboard.org/nightlies/
Platform: UNKNOWN
Classifier: Development Status :: 4 - Beta
Classifier: Environment :: Console
Classifier: Intended Audience :: Developers
Classifier: License :: OSI Approved :: MIT License
Classifier: Operating System :: OS Independent
Classifier: Programming Language :: Python
Classifier: Topic :: Software Development
